redbird/__init__.py
redbird/_version.py
redbird/base.py
redbird/dummy.py
redbird/exc.py
redbird/oper.py
redbird/packages.py
redbird/templates.py
redbird/logging/__init__.py
redbird/logging/handler.py
redbird/repos/__init__.py
redbird/repos/csv.py
redbird/repos/json.py
redbird/repos/memory.py
redbird/repos/mongo.py
redbird/repos/rest.py
redbird/repos/sqlalchemy.py
redbird/sql/__init__.py
redbird/sql/expressions.py
redbird/test/__init__.py
redbird/test/conftest.py
redbird/test/test_build.py
redbird/test/test_creation.py
redbird/test/common/__init__.py
redbird/test/common/conftest.py
redbird/test/common/test_common.py
redbird/test/common/test_oper.py
redbird/test/logging/__init__.py
redbird/test/logging/test_handler.py
redbird/test/repo/__init__.py
redbird/test/repo/test_csv.py
redbird/test/repo/test_json.py
redbird/test/repo/test_mongo.py
redbird/test/repo/test_sql.py
redbird/test/sql/__init__.py
redbird/test/sql/conftest.py
redbird/test/sql/test_create.py
redbird/test/sql/test_operations.py
redbird/test/sql/test_transactions.py
redbird/test/sql/operations/__init__.py
redbird/test/sql/operations/test_delete.py
redbird/test/sql/operations/test_insert.py
redbird/test/sql/operations/test_select.py
redbird/test/sql/operations/test_update.py
redbird/test/sql/table/__init__.py
redbird/test/sql/table/conftest.py
redbird/test/sql/table/test_delitem.py
redbird/test/sql/table/test_getitem.py
redbird/test/utils/__init__.py
redbird/test/utils/test_importing.py
redbird/utils/__init__.py
redbird/utils/case.py
redbird/utils/deprecate.py
redbird/utils/importing.py
redbird/utils/query.py
redbird-0.7.1.dist-info/LICENSE
redbird-0.7.1.dist-info/METADATA
redbird-0.7.1.dist-info/WHEEL
redbird-0.7.1.dist-info/top_level.txt
redbird-0.7.1.dist-info/RECORD
