Metadata-Version: 2.1
Name: redbird
Version: 0.7.1
Summary: Repository Patterns for Python
Author-email: Mikael Koli <koli.mikael@gmail.com>
License: MIT License
Project-URL: Homepage, https://github.com/Miksus/red-bird
Project-URL: Documentation, https://red-bird.readthedocs.io
Project-URL: Funding, https://github.com/sponsors/Miksus
Project-URL: Source, https://github.com/Miksus/red-bird
Project-URL: Changelog, https://red-bird.readthedocs.io/en/stable/versions.html
Classifier: License :: OSI Approved :: MIT License
Classifier: Operating System :: OS Independent
Classifier: Programming Language :: Python
Classifier: Programming Language :: Python :: 3
Classifier: Programming Language :: Python :: 3.7
Classifier: Programming Language :: Python :: 3.8
Classifier: Programming Language :: Python :: 3.9
Classifier: Programming Language :: Python :: 3.10
Classifier: Programming Language :: Python :: 3.11
Classifier: Intended Audience :: Developers
Classifier: Topic :: Database
Requires-Python: >=3.7
Provides-Extra: full
Provides-Extra: test
Provides-Extra: sql
Provides-Extra: mongodb
Provides-Extra: rest
License-File: LICENSE
